setup.py
multitest/__init__.py
multitest/__main__.py
multitest/runner.py
multitest.egg-info/PKG-INFO
multitest.egg-info/SOURCES.txt
multitest.egg-info/dependency_links.txt
multitest.egg-info/top_level.txt
test/test_success.py