Metadata-Version: 1.1
Name: multitest
Version: 0.1.2
Summary: Multiprocess Unittest Runner
Home-page: https://github.com/tcooc/multitest
Author: tcooc
Author-email: thcooc at gmail dot com
License: MIT License
Download-URL: https://pypi.python.org/pypi/multitest
Keywords: unittest test multiprocessing
Platform: any
Classifier: Development Status :: 3 - Alpha
Classifier: Intended Audience :: Developers
Classifier: License :: OSI Approved :: MIT License
Classifier: Programming Language :: Python
Classifier: Programming Language :: Python :: 2.7
Classifier: Topic :: Software Development :: Testing
